MANIFEST.in
README.rst
setup.py
fbi/__init__.py
fbi/accessory.py
fbi/client.py
fbi/decode.py
fbi/encode.py
fbi/fbi.py
fbi/init.py
fbi/salt.py
fbi/settings.py
fbi.egg-info/PKG-INFO
fbi.egg-info/SOURCES.txt
fbi.egg-info/dependency_links.txt
fbi.egg-info/entry_points.txt
fbi.egg-info/requires.txt
fbi.egg-info/top_level.txt
fbi.egg-info/zip-safe
fbi/config/argparse.txt
fbi/config/fbi.cfg
fbi/config/messages.txt