Metadata-Version: 1.1
Name: fbi
Version: 0.1a7
Summary: The password encryption utility
Home-page: https://github.com/korniichuk/fbi/
Author: Ruslan Korniichuk
Author-email: ruslan.korniichuk@gmail.com
License: Public Domain
Download-URL: https://github.com/korniichuk/fbi/archive/0.1.zip
Keywords: cryptography,fbi,key,python,python2
Platform: Linux
Classifier: Development Status :: 3 - Alpha
Classifier: Environment :: Console
Classifier: Intended Audience :: Developers
Classifier: Operating System :: POSIX
Classifier: Operating System :: POSIX :: Linux
Classifier: Programming Language :: Python
Classifier: Programming Language :: Python :: 2
Classifier: Programming Language :: Python :: 2.7
Classifier: Programming Language :: Python :: 2 :: Only
Classifier: Topic :: Security
Classifier: Topic :: Security :: Cryptography
Classifier: Topic :: Software Development
Classifier: Topic :: Software Development :: Libraries
Classifier: Topic :: Software Development :: Libraries :: Python Modules
Classifier: Topic :: Utilities
